README.md
setup.py
fraud_detector_unisoft.egg-info/PKG-INFO
fraud_detector_unisoft.egg-info/SOURCES.txt
fraud_detector_unisoft.egg-info/dependency_links.txt
fraud_detector_unisoft.egg-info/requires.txt
fraud_detector_unisoft.egg-info/top_level.txt
frauddetector/__init__.py
frauddetector/admin.py
frauddetector/apps.py
frauddetector/checker.py
frauddetector/exceptions.py
frauddetector/models.py
frauddetector/tests.py
frauddetector/views.py