Metadata-Version: 2.1
Name: fraud-detector-unisoft
Version: 0.0.1
Summary: Library for fraud_detecting
Home-page: 
Author: Saidkomil Makhamadkhujayev
Author-email: msaidkomils@gmail.com
License: MIT
Classifier: Intended Audience :: Developers
Classifier: License :: OSI Approved :: MIT License
Classifier: Programming Language :: Python
Classifier: Programming Language :: Python :: 3
Classifier: Programming Language :: Python :: 3.6
Classifier: Programming Language :: Python :: 3.7
Classifier: Programming Language :: Python :: 3.8
Classifier: Programming Language :: Python :: 3.9
Classifier: Operating System :: OS Independent
